ams/__init__.py
ams/__main__.py
ams/_version.py
ams/cli.py
ams/interface.py
ams/main.py
ams/report.py
ams/shared.py
ams/system.py
ams/cases/5bus/pjm5bus_demo.json
ams/cases/5bus/pjm5bus_demo.xlsx
ams/cases/5bus/pjm5bus_ev.xlsx
ams/cases/5bus/pjm5bus_jumper.xlsx
ams/cases/hawaii40/Hawaii40.m
ams/cases/ieee123/ieee123.xlsx
ams/cases/ieee123/ieee123_regcv1.xlsx
ams/cases/ieee14/ieee14.json
ams/cases/ieee14/ieee14.raw
ams/cases/ieee14/ieee14_conn.xlsx
ams/cases/ieee14/ieee14_uced.xlsx
ams/cases/ieee39/ieee39.xlsx
ams/cases/ieee39/ieee39_uced.xlsx
ams/cases/ieee39/ieee39_uced_esd1.xlsx
ams/cases/ieee39/ieee39_uced_pvd1.xlsx
ams/cases/ieee39/ieee39_uced_vis.xlsx
ams/cases/matpower/benchmark.json
ams/cases/matpower/case118.m
ams/cases/matpower/case14.m
ams/cases/matpower/case300.m
ams/cases/matpower/case39.m
ams/cases/matpower/case5.m
ams/cases/matpower/case_ACTIVSg2000.m
ams/cases/npcc/npcc.m
ams/cases/npcc/npcc_uced.xlsx
ams/cases/pglib/pglib_opf_case39_epri__api.m
ams/cases/wecc/wecc.m
ams/cases/wecc/wecc_uced.xlsx
ams/core/__init__.py
ams/core/common.py
ams/core/documenter.py
ams/core/matprocessor.py
ams/core/model.py
ams/core/param.py
ams/core/service.py
ams/core/symprocessor.py
ams/core/var.py
ams/extension/__init__.py
ams/extension/eva.py
ams/io/__init__.py
ams/io/json.py
ams/io/matpower.py
ams/io/psse.py
ams/io/pypower.py
ams/io/xlsx.py
ams/models/__init__.py
ams/models/area.py
ams/models/bus.py
ams/models/cost.py
ams/models/group.py
ams/models/info.py
ams/models/line.py
ams/models/reserve.py
ams/models/shunt.py
ams/models/timeslot.py
ams/models/zone.py
ams/models/distributed/__init__.py
ams/models/distributed/esd1.py
ams/models/distributed/ev.py
ams/models/distributed/pvd1.py
ams/models/renewable/__init__.py
ams/models/renewable/regc.py
ams/models/static/__init__.py
ams/models/static/gen.py
ams/models/static/pq.py
ams/opt/__init__.py
ams/opt/constraint.py
ams/opt/exprcalc.py
ams/opt/expression.py
ams/opt/objective.py
ams/opt/omodel.py
ams/opt/optzbase.py
ltbams-1.1.1.dist-info/METADATA
ltbams-1.1.1.dist-info/WHEEL
ltbams-1.1.1.dist-info/entry_points.txt
ltbams-1.1.1.dist-info/top_level.txt
ltbams-1.1.1.dist-info/RECORD
