Metadata-Version: 2.4
Name: ltbams
Version: 1.1.1
Summary: Python software for scheduling modeling and co-simulation with dynamics.
Home-page: https://github.com/CURENT/ams
Author: Jinning Wang
Author-email: Jinning Wang <jinninggm@gmail.com>
License: GPL-3.0-or-later
Classifier: Development Status :: 4 - Beta
Classifier: Natural Language :: English
Classifier: Programming Language :: Python :: 3
Classifier: License :: OSI Approved :: GNU General Public License v3 or later (GPLv3+)
Classifier: Environment :: Console
Requires-Dist: kvxopt>=1.3.2.1
Requires-Dist: numpy
Requires-Dist: scipy
Requires-Dist: sympy!=1.10.0,>=1.6
Requires-Dist: pandas
Requires-Dist: matplotlib
Requires-Dist: psutil
Requires-Dist: openpyxl
Requires-Dist: andes>=1.9.3
Requires-Dist: pybind11
Requires-Dist: cvxpy
Requires-Dist: cffi
Provides-Extra: dev
Requires-Dist: pytest; extra == "dev"
Requires-Dist: pytest-cov; extra == "dev"
Requires-Dist: coverage; extra == "dev"
Requires-Dist: flake8; extra == "dev"
Requires-Dist: numpydoc; extra == "dev"
Requires-Dist: toml; extra == "dev"
Provides-Extra: nlp
Requires-Dist: PYPOWER; extra == "nlp"
Requires-Dist: pyoptinterface; extra == "nlp"
Requires-Dist: gurobipy; extra == "nlp"
Requires-Dist: gurobi-optimods; extra == "nlp"
Provides-Extra: doc
Requires-Dist: pandoc; extra == "doc"
Requires-Dist: ipython; extra == "doc"
Requires-Dist: sphinx; extra == "doc"
Requires-Dist: pydata-sphinx-theme; extra == "doc"
Requires-Dist: numpydoc; extra == "doc"
Requires-Dist: sphinx-copybutton; extra == "doc"
Requires-Dist: sphinx-panels; extra == "doc"
Requires-Dist: myst-parser; extra == "doc"
Requires-Dist: nbsphinx; extra == "doc"
Dynamic: author
Dynamic: home-page
